Metadata-Version: 2.1
Name: geostggc
Version: 1.2
Summary: A geo-spatiotemporal grid to graph converter
Home-page: https://github.com/ding05/geo_st_grid_graph_converter
Author: Ding Ning
Author-email: ding.ning@pg.canterbury.ac.nz
License: MIT
Platform: UNKNOWN
